Metadata-Version: 2.1
Name: boto3-handlers
Version: 1.0.0
Summary: Python Boto3 Dynamo DB Handler
Home-page: https://github.com/alexsmithx6-0z1nm/boto3_handlers
Author: Alexander Smith
Author-email: alexsmithx6@0z1nm.onmicrosoft.com
License: MIT
Project-URL: Documentation, https://boto3.amazonaws.com/v1/documentation/api/latest/index.html
Project-URL: Source, https://github.com/alexsmithx6-0z1nm/boto3_handlers
Platform: UNKNOWN
Classifier: Development Status :: 1 - Planning
Classifier: Intended Audience :: Developers
Classifier: License :: OSI Approved :: MIT License
Classifier: Operating System :: POSIX :: Linux
Classifier: Programming Language :: Python :: 3
License-File: LICENSE
